CHANGES.txt
DEPENDENCES.txt
README.txt
setup.py
src/ng/__init__.py
src/ng.app.mailfeed.egg-info/PKG-INFO
src/ng.app.mailfeed.egg-info/SOURCES.txt
src/ng.app.mailfeed.egg-info/dependency_links.txt
src/ng.app.mailfeed.egg-info/namespace_packages.txt
src/ng.app.mailfeed.egg-info/not-zip-safe
src/ng.app.mailfeed.egg-info/requires.txt
src/ng.app.mailfeed.egg-info/top_level.txt
src/ng/app/__init__.py
src/ng/app/mailfeed/__init__.py
src/ng/app/mailfeed/configure.zcml
src/ng/app/mailfeed/interfaces.py
src/ng/app/mailfeed/mailfeed.py
src/ng/app/mailfeed/ng.app.mailfeed.txt
src/ng/app/mailfeed/addresses/__init__.py
src/ng/app/mailfeed/addresses/addresses.py
src/ng/app/mailfeed/addresses/addressesannotableadapter.py
src/ng/app/mailfeed/addresses/addressesutilitableadapter.py
src/ng/app/mailfeed/addresses/configure.zcml
src/ng/app/mailfeed/addresses/interfaces.py
src/ng/app/mailfeed/addresses/ng.app.mailfeed.addresses.txt
src/ng/app/mailfeed/addresses/browser/__init__.py
src/ng/app/mailfeed/addresses/browser/configure.zcml
src/ng/app/mailfeed/addresses/browser/widgets.py
src/ng/app/mailfeed/etc/ng.app.mailfeed-configure.zcml
src/ng/app/mailfeed/mailtemplate/__init__.py
src/ng/app/mailfeed/mailtemplate/configure.zcml
src/ng/app/mailfeed/mailtemplate/interfaces.py
src/ng/app/mailfeed/mailtemplate/mailtemplate.py
src/ng/app/mailfeed/mailtemplate/mailtemplateannotableadapter.py
src/ng/app/mailfeed/mailtemplate/mailtemplateutilitableadapter.py
src/ng/app/mailfeed/mailtemplate/ng.app.mailfeed.mailtemplate.txt
src/ng/app/mailfeed/mailtemplate/browser/__init__.py
src/ng/app/mailfeed/mailtemplate/browser/configure.zcml
src/ng/app/mailfeed/sender/__init__.py
src/ng/app/mailfeed/sender/configure.zcml
src/ng/app/mailfeed/sender/interfaces.py
src/ng/app/mailfeed/sender/ng.app.mailfeed.sender.txt
src/ng/app/mailfeed/sender/sender.py
src/ng/app/mailfeed/sender/senderannotableadapter.py
src/ng/app/mailfeed/sender/senderutilitableadapter.py
src/ng/app/mailfeed/sender/browser/__init__.py
src/ng/app/mailfeed/sender/browser/configure.zcml